isostatic/__init__.py
isostatic/release.py
isostatic/constants/__init__.py
isostatic/constants/constantsSI.py
isostatic/constants/constantsSymbols.py
isostatic/constants/test/__init__.py
isostatic/elements/__init__.py
isostatic/elements/beams.py
isostatic/elements/test/__init__.py
isostatic/elements/test/test_beam_inits.py
isostatic/loads/__init__.py
isostatic/loads/loads.py
isostatic/loads/test/__init__.py
isostatic/loads/test/test_loads.py
isostatic/points/__init__.py
isostatic/points/point.py
isostatic/points/test/__init__.py
isostatic/points/test/test_point.py
isostatic/points/test/test_point_support.py
isostatic/structures/__init__.py
isostatic/structures/structure.py
isostatic/structures/test/__init__.py
isostatic/structures/test/test_init_structure.py
isostatic/supports/__init__.py
isostatic/supports/support.py
isostatic/supports/test/__init__.py
isostatic/supports/test/test_support.py
isostatic/tests/__init__.py
isostatic-0.0.8.dist-info/LICENSE
isostatic-0.0.8.dist-info/METADATA
isostatic-0.0.8.dist-info/WHEEL
isostatic-0.0.8.dist-info/top_level.txt
isostatic-0.0.8.dist-info/RECORD
